hecalc/__init__.py
hecalc/date_calculation.py
hecalc/GUI/__init__.py
hecalc/GUI/base_GUI.py
hecalc/GUI/main_GUI.py
hecalc/linear_propagation.py
hecalc/main.py
hecalc/montecarlo.py
hecalc-1.0.1.dist-info/COPYING
hecalc-1.0.1.dist-info/WHEEL
hecalc-1.0.1.dist-info/METADATA
hecalc-1.0.1.dist-info/RECORD
